octotools/__init__.py
octotools/localtime.py
octotools-1.0.dist-info/DESCRIPTION.rst
octotools-1.0.dist-info/METADATA
octotools-1.0.dist-info/RECORD
octotools-1.0.dist-info/WHEEL
octotools-1.0.dist-info/metadata.json
octotools-1.0.dist-info/top_level.txt
